{"data":{"article":{},"attachments":{"media_keys":["3_2038764021386489856"],"media_source_tweet_id":["2038764025920520263"]},"author_id":"2031852608684769280","conversation_id":"2039251203327250920","created_at":"2026-04-01T07:59:08.000Z","edit_controls":{"edits_remaining":5,"is_edit_eligible":false,"editable_until":"2026-04-01T08:59:08.000Z"},"edit_history_tweet_ids":["2039251203327250920"],"entities":{"mentions":[{"start":3,"end":14,"username":"x1aoyu_TvT","id":"1795809659237879808"}],"urls":[{"start":27,"end":50,"url":"https://t.co/bibhw2VHwf","expanded_url":"https://x.com/x1aoyu_TvT/status/2038764025920520263/photo/1","display_url":"pic.x.com/bibhw2VHwf","media_key":"3_2038764021386489856"}]},"geo":{},"id":"2039251203327250920","lang":"zh","note_tweet":{"entities":{}},"possibly_sensitive":false,"public_metrics":{"retweet_count":45,"reply_count":0,"like_count":0,"quote_count":0,"bookmark_count":0,"impression_count":0},"referenced_tweets":[{"type":"retweeted","id":"2038764025920520263"}],"reply_settings":"everyone","text":"RT @x1aoyu_TvT: 我已经预约了整容医生 https://t.co/bibhw2VHwf"},"includes":{"media":[{"height":629,"media_key":"3_2038764021386489856","public_metrics":{},"type":"photo","url":"https://pbs.twimg.com/media/HEslE1uWsAAuRcr.jpg","width":1206}],"users":[{"created_at":"2026-03-11T22:00:35.000Z","description":"小希Kiyumi/0121/躁郁/焦虑/被害妄想/overdose/清水推/不聊骚努力活着中/第n世就只有这个号现在在用/顺女\n🚪188/288/588/888","id":"2031852608684769280","location":"天空","name":"Kiyumi","pinned_tweet_id":"2038042420907307315","profile_image_url":"https://pbs.twimg.com/profile_images/2038043426747465728/9vVwm0uj_normal.jpg","protected":false,"public_metrics":{"followers_count":93,"following_count":27,"tweet_count":168,"listed_count":0,"like_count":105,"media_count":25},"username":"Kiyumi_kamisama","verified":false},{"created_at":"2024-05-29T13:35:46.000Z","description":"EN/DE/FR/CN｜📍德國 ｜叫我xiaoyu｜台獨精日支黑｜pink网左激女男权出门左拐｜随缘接盒｜歡迎互fo^^","id":"1795809659237879808","location":"下北沢","name":"你抱著我掉眼淚說這世界太複雜","pinned_tweet_id":"2030418351139209420","profile_image_url":"https://pbs.twimg.com/profile_images/1952848575194353664/t7Ku58Fz_normal.jpg","protected":false,"public_metrics":{"followers_count":1233,"following_count":198,"tweet_count":934,"listed_count":4,"like_count":1514,"media_count":133},"username":"x1aoyu_TvT","verified":false}],"tweets":[{"article":{},"attachments":{"media_keys":["3_2038764021386489856"],"media_source_tweet_id":["2038764025920520263"]},"author_id":"2031852608684769280","conversation_id":"2039251203327250920","created_at":"2026-04-01T07:59:08.000Z","edit_controls":{"edits_remaining":5,"is_edit_eligible":false,"editable_until":"2026-04-01T08:59:08.000Z"},"edit_history_tweet_ids":["2039251203327250920"],"entities":{"mentions":[{"start":3,"end":14,"username":"x1aoyu_TvT","id":"1795809659237879808"}],"urls":[{"start":27,"end":50,"url":"https://t.co/bibhw2VHwf","expanded_url":"https://x.com/x1aoyu_TvT/status/2038764025920520263/photo/1","display_url":"pic.x.com/bibhw2VHwf","media_key":"3_2038764021386489856"}]},"geo":{},"id":"2039251203327250920","lang":"zh","note_tweet":{"entities":{}},"possibly_sensitive":false,"public_metrics":{"retweet_count":45,"reply_count":0,"like_count":0,"quote_count":0,"bookmark_count":0,"impression_count":0},"referenced_tweets":[{"type":"retweeted","id":"2038764025920520263"}],"reply_settings":"everyone","text":"RT @x1aoyu_TvT: 我已经预约了整容医生 https://t.co/bibhw2VHwf"},{"article":{},"attachments":{"media_keys":["3_2038764021386489856"]},"author_id":"1795809659237879808","conversation_id":"2038764025920520263","created_at":"2026-03-30T23:43:16.000Z","edit_controls":{"edits_remaining":5,"is_edit_eligible":true,"editable_until":"2026-03-31T00:43:16.000Z"},"edit_history_tweet_ids":["2038764025920520263"],"entities":{"urls":[{"start":11,"end":34,"url":"https://t.co/bibhw2VHwf","expanded_url":"https://x.com/x1aoyu_TvT/status/2038764025920520263/photo/1","display_url":"pic.x.com/bibhw2VHwf","media_key":"3_2038764021386489856"}]},"geo":{},"id":"2038764025920520263","lang":"zh","note_tweet":{"entities":{}},"possibly_sensitive":false,"public_metrics":{"retweet_count":45,"reply_count":82,"like_count":1293,"quote_count":8,"bookmark_count":44,"impression_count":108607},"reply_settings":"everyone","text":"我已经预约了整容医生 https://t.co/bibhw2VHwf"}]}}
