{"data":{"article":{},"attachments":{"media_keys":["3_2040745544579002369","3_2040745544557932544"],"media_source_tweet_id":["2040745555089858794","2040745555089858794"]},"author_id":"2031852608684769280","conversation_id":"2041416008020512842","created_at":"2026-04-07T07:21:18.000Z","edit_controls":{"edits_remaining":5,"is_edit_eligible":false,"editable_until":"2026-04-07T08:21:18.000Z"},"edit_history_tweet_ids":["2041416008020512842"],"entities":{"mentions":[{"start":3,"end":17,"username":"pienangelkabu","id":"2024877578297933824"}],"urls":[{"start":53,"end":76,"url":"https://t.co/guSq2RYRI2","expanded_url":"https://x.com/pienangelkabu/status/2040745555089858794/photo/1","display_url":"pic.x.com/guSq2RYRI2","media_key":"3_2040745544579002369"},{"start":53,"end":76,"url":"https://t.co/guSq2RYRI2","expanded_url":"https://x.com/pienangelkabu/status/2040745555089858794/photo/1","display_url":"pic.x.com/guSq2RYRI2","media_key":"3_2040745544557932544"}]},"geo":{},"id":"2041416008020512842","lang":"en","note_tweet":{"entities":{}},"possibly_sensitive":false,"public_metrics":{"retweet_count":1374,"reply_count":0,"like_count":0,"quote_count":0,"bookmark_count":0,"impression_count":0},"referenced_tweets":[{"type":"retweeted","id":"2040745555089858794"}],"reply_settings":"everyone","text":"RT @pienangelkabu: WE GOT TO SEE AME’S OTHER EYE !!! https://t.co/guSq2RYRI2"},"includes":{"media":[{"height":1302,"media_key":"3_2040745544579002369","public_metrics":{},"type":"photo","url":"https://pbs.twimg.com/media/HFIvQq2XsAEYJO-.jpg","width":1650},{"height":274,"media_key":"3_2040745544557932544","public_metrics":{},"type":"photo","url":"https://pbs.twimg.com/media/HFIvQqxWMAA2H_b.jpg","width":288}],"users":[{"created_at":"2026-03-11T22:00:35.000Z","description":"小希Kiyumi/0121/躁郁/焦虑/被害妄想/overdose/清水推/不聊骚努力活着中/第n世就只有这个号现在在用/顺女/不想被说像任何人/(´-ω-`)@ljiy142044 \n🚪188/288/588/888","entities":{"description":{"mentions":[{"start":80,"end":91,"username":"ljiy142044"}]}},"id":"2031852608684769280","location":"天空","name":"Kiyumi","pinned_tweet_id":"2038042420907307315","profile_image_url":"https://pbs.twimg.com/profile_images/2038043426747465728/9vVwm0uj_normal.jpg","protected":false,"public_metrics":{"followers_count":170,"following_count":29,"tweet_count":298,"listed_count":0,"like_count":196,"media_count":39},"username":"Kiyumi_kamisama","verified":false},{"created_at":"2026-02-20T16:03:39.000Z","description":"#jiraitwt ꒱ ᕱ⑅ᕱ #放浪者’s bun angel wife ♥︎ ໒꒰ྀི´ ˘ ` ꒱ྀིა 🪽地雷女子 🗝 ༝ @heart4kiyo | wan/scara yumes DNI ♪ ꒰ unless i int first ꒱","entities":{"url":{"urls":[{"start":0,"end":23,"url":"https://t.co/Xld91zP2Z4","expanded_url":"https://lit.link/en/pienkabu","display_url":"lit.link/en/pienkabu"}]},"description":{"hashtags":[{"start":0,"end":9,"tag":"jiraitwt"},{"start":16,"end":20,"tag":"放浪者"}],"mentions":[{"start":66,"end":77,"username":"heart4kiyo"}]}},"id":"2024877578297933824","location":"15 ⑅ ifb most . read byf →","name":"ʚ riri ɞ","pinned_tweet_id":"2030334261882954086","profile_image_url":"https://pbs.twimg.com/profile_images/2039540313384251392/hsIfsvLR_normal.jpg","protected":false,"public_metrics":{"followers_count":522,"following_count":424,"tweet_count":1447,"listed_count":10,"like_count":3971,"media_count":412},"url":"https://t.co/Xld91zP2Z4","username":"pienangelkabu","verified":true},{"created_at":"2026-02-20T16:03:39.000Z","description":"#jiraitwt ꒱ ᕱ⑅ᕱ #放浪者’s bun angel wife ♥︎ ໒꒰ྀི´ ˘ ` ꒱ྀིა 🪽地雷女子 🗝 ༝ @heart4kiyo | wan/scara yumes DNI ♪ ꒰ unless i int first ꒱","entities":{"url":{"urls":[{"start":0,"end":23,"url":"https://t.co/Xld91zP2Z4","expanded_url":"https://lit.link/en/pienkabu","display_url":"lit.link/en/pienkabu"}]},"description":{"hashtags":[{"start":0,"end":9,"tag":"jiraitwt"},{"start":16,"end":20,"tag":"放浪者"}],"mentions":[{"start":66,"end":77,"username":"heart4kiyo"}]}},"id":"2024877578297933824","location":"15 ⑅ ifb most . read byf →","name":"ʚ riri ɞ","pinned_tweet_id":"2030334261882954086","profile_image_url":"https://pbs.twimg.com/profile_images/2039540313384251392/hsIfsvLR_normal.jpg","protected":false,"public_metrics":{"followers_count":522,"following_count":424,"tweet_count":1447,"listed_count":10,"like_count":3971,"media_count":412},"url":"https://t.co/Xld91zP2Z4","username":"pienangelkabu","verified":false}],"tweets":[{"article":{},"attachments":{"media_keys":["3_2040745544579002369","3_2040745544557932544"],"media_source_tweet_id":["2040745555089858794","2040745555089858794"]},"author_id":"2031852608684769280","conversation_id":"2041416008020512842","created_at":"2026-04-07T07:21:18.000Z","edit_controls":{"edits_remaining":5,"is_edit_eligible":false,"editable_until":"2026-04-07T08:21:18.000Z"},"edit_history_tweet_ids":["2041416008020512842"],"entities":{"mentions":[{"start":3,"end":17,"username":"pienangelkabu","id":"2024877578297933824"}],"urls":[{"start":53,"end":76,"url":"https://t.co/guSq2RYRI2","expanded_url":"https://x.com/pienangelkabu/status/2040745555089858794/photo/1","display_url":"pic.x.com/guSq2RYRI2","media_key":"3_2040745544579002369"},{"start":53,"end":76,"url":"https://t.co/guSq2RYRI2","expanded_url":"https://x.com/pienangelkabu/status/2040745555089858794/photo/1","display_url":"pic.x.com/guSq2RYRI2","media_key":"3_2040745544557932544"}]},"geo":{},"id":"2041416008020512842","lang":"en","note_tweet":{"entities":{}},"possibly_sensitive":false,"public_metrics":{"retweet_count":1374,"reply_count":0,"like_count":0,"quote_count":0,"bookmark_count":0,"impression_count":0},"referenced_tweets":[{"type":"retweeted","id":"2040745555089858794"}],"reply_settings":"everyone","text":"RT @pienangelkabu: WE GOT TO SEE AME’S OTHER EYE !!! https://t.co/guSq2RYRI2"},{"article":{},"attachments":{"media_keys":["3_2040745544579002369","3_2040745544557932544"]},"author_id":"2024877578297933824","conversation_id":"2040745555089858794","created_at":"2026-04-05T10:57:10.000Z","edit_controls":{"edits_remaining":5,"is_edit_eligible":true,"editable_until":"2026-04-05T11:57:10.000Z"},"edit_history_tweet_ids":["2040745555089858794"],"entities":{"urls":[{"start":34,"end":57,"url":"https://t.co/guSq2RYRI2","expanded_url":"https://x.com/pienangelkabu/status/2040745555089858794/photo/1","display_url":"pic.x.com/guSq2RYRI2","media_key":"3_2040745544579002369"},{"start":34,"end":57,"url":"https://t.co/guSq2RYRI2","expanded_url":"https://x.com/pienangelkabu/status/2040745555089858794/photo/1","display_url":"pic.x.com/guSq2RYRI2","media_key":"3_2040745544557932544"}]},"geo":{},"id":"2040745555089858794","lang":"en","note_tweet":{"entities":{}},"possibly_sensitive":false,"public_metrics":{"retweet_count":1374,"reply_count":12,"like_count":12733,"quote_count":55,"bookmark_count":907,"impression_count":359847},"reply_settings":"everyone","text":"WE GOT TO SEE AME’S OTHER EYE !!! https://t.co/guSq2RYRI2"}]}}
